{"cameraMode":{"drawMode":0,"name":"Shaded","section":"Shading Mode"},"sceneLighting":true,"audioPlay":false,"sceneViewState":{"m_AlwaysRefresh":false,"showFog":true,"showSkybox":true,"showFlares":true,"showImageEffects":true,"showParticleSystems":true,"showVisualEffectGraphs":true,"m_FxEnabled":true},"in2DMode":false,"pivot":{"x":-0.4895891845226288,"y":1.536309838294983,"z":-1.0660324096679688},"rotation":{"x":-0.2521941661834717,"y":-0.021193020045757295,"z":0.005524799227714539,"w":-0.96742844581604},"size":10.0,"orthographic":false}